seqgentools/__init__.py
seqgentools/sequence.py
seqgentools/algorithms/__init__.py
seqgentools/algorithms/combinatorics.py
seqgentools/algorithms/extendables.py
seqgentools/algorithms/hssgen.py
seqgentools-0.0.16.dist-info/DESCRIPTION.rst
seqgentools-0.0.16.dist-info/METADATA
seqgentools-0.0.16.dist-info/RECORD
seqgentools-0.0.16.dist-info/WHEEL
seqgentools-0.0.16.dist-info/metadata.json
seqgentools-0.0.16.dist-info/top_level.txt
tests/__init__.py
tests/test_algorithms.py
tests/test_primitives.py
